MANIFEST.in
README.md
quicktest.py
settings_test.py
setup.py
django_facebook_posts.egg-info/PKG-INFO
django_facebook_posts.egg-info/SOURCES.txt
django_facebook_posts.egg-info/dependency_links.txt
django_facebook_posts.egg-info/not-zip-safe
django_facebook_posts.egg-info/requires.txt
django_facebook_posts.egg-info/top_level.txt
facebook_posts/__init__.py
facebook_posts/__init__.pyc
facebook_posts/admin.py
facebook_posts/admin.pyc
facebook_posts/factories.py
facebook_posts/factories.pyc
facebook_posts/models.py
facebook_posts/models.pyc
facebook_posts/tests.py
facebook_posts/tests.pyc
facebook_posts/migrations/0001_initial.py
facebook_posts/migrations/0001_initial.pyc
facebook_posts/migrations/0002_auto__add_comment__del_field_post_likes__del_field_post_comments__add_.py
facebook_posts/migrations/0003_auto__add_field_comment_likes_real_count.py
facebook_posts/migrations/0004_auto__add_field_post_expanded_height__add_field_post_expanded_width.py
facebook_posts/migrations/0005_auto__chg_field_post_story__chg_field_post_description__chg_field_post.py
facebook_posts/migrations/0006_auto__chg_field_post_source.py
facebook_posts/migrations/0007_auto.py
facebook_posts/migrations/0008_auto__chg_field_post_updated_time.py
facebook_posts/migrations/0008_auto__chg_field_post_updated_time.pyc
facebook_posts/migrations/0009_auto__chg_field_post_name.py
facebook_posts/migrations/0010_auto__add_field_post_shares_json__add_field_post_shares_count.py
facebook_posts/migrations/0011_auto__del_field_comment_likes_real_count__del_field_post_comments_real.py
facebook_posts/migrations/0012_auto.py
facebook_posts/migrations/0013_auto__chg_field_post_link.py
facebook_posts/migrations/0014_change_m2m_to_m2m_history.py
facebook_posts/migrations/0015_auto__chg_field_post_link.py
facebook_posts/migrations/0016_auto__del_comment__chg_field_post_comments_count__chg_field_post_graph.py
facebook_posts/migrations/0017_auto__chg_field_post_author_id.py
facebook_posts/migrations/0018_auto__chg_field_post_type__add_index_post_type.py
facebook_posts/migrations/0019_auto__chg_field_post_graph_id__chg_field_post_link.py
facebook_posts/migrations/__init__.py
facebook_posts/migrations/__init__.pyc
facebook_posts/sql/post.postgresql_psycopg2.sql