Metadata-Version: 1.1
Name: django-facebook-posts
Version: 0.6.1
Summary: Django implementation for Facebook Graph API Posts
Home-page: https://github.com/ramusus/django-facebook-posts
Author: ramusus
Author-email: ramusus@gmail.com
License: BSD
Download-URL: http://pypi.python.org/pypi/django-facebook-posts
Platform: UNKNOWN
Classifier: Development Status :: 4 - Beta
Classifier: Environment :: Web Environment
Classifier: Intended Audience :: Developers
Classifier: License :: OSI Approved :: BSD License
Classifier: Operating System :: OS Independent
Classifier: Programming Language :: Python
Classifier: Topic :: Software Development :: Libraries :: Python Modules
